{"is_source_file": true, "format": "JavaScript", "description": "Defines a Blits component 'DetailsModal' used to display item details in a modal dialog, including UI elements, styling, and interaction methods.", "external_files": ["@lightningjs/blits", "../theme/theme.js"], "external_methods": [], "published": ["close", "requestDelete", "esign"], "classes": [{"name": "DetailsModal", "description": "A Lightning.js Blits component for displaying details of an item with actions like close, delete, and electronic signature."}], "methods": [{"name": "close", "description": "Emits a 'close' event to close the modal."}, {"name": "requestDelete", "description": "Emits a 'delete' event to request deletion of the item."}, {"name": "esign", "description": "Emits an 'esign' event for electronic signature approval, passing the item ID."}], "calls": ["$emit({ type: 'close' })", "$emit({ type: 'delete' })", "$emit({ type: 'esign', artifact: { intent: 'approve', bindTo: this.item?.id } })"], "search-terms": ["DetailsModal", "LightningBlits", "modal component", "item details display", "Vue.js component", "LightningJS", "event emission"], "state": 2, "file_id": 46, "knowledge_revision": 94, "git_revision": "", "ctags": [], "hash": "c2691c59f16b811d3344e16b350bad28", "format-version": 4, "code-base-name": "vod_menus_frontend", "filename": "vod_menus_frontend/src/components/DetailsModal.js", "revision_history": [{"94": ""}]}